[
  {
    "movieTitle": "Iron man2",
    "movieGender": "action",
    "roomNumber": 3,
    "movieFormat": "3D",
    "moviePrice": 8.0
  },
  {
    "movieTitle": "Scooby Doo",
    "movieGender": "action",
    "roomNumber": 6,
    "movieFormat": "3D",
    "moviePrice": 8.0
  },
  {
    "movieTitle": "Iron man",
    "movieGender": "action",
    "roomNumber": 1,
    "movieFormat": "2D",
    "moviePrice": 6.5
  },
  {
    "movieTitle": "Avenger End Game",
    "movieGender": "action",
    "roomNumber": 2,
    "movieFormat": "2D",
    "moviePrice": 6.5
  }
]
